<?xml version='1.0' encoding='utf-8' ?>
<!DOCTYPE table PUBLIC "-//OASIS//DTD DocBook XML V4.5//EN" "http://www.oasis-open.org/docbook/xml/4.5/docbookx.dtd" [
]>

<table id="tabl-richeditor-Style_classes_and_corresponding_skin_parameters">
	<title>Style classes (selectors) and corresponding skin parameters</title>
	<tgroup cols="3">
		<colspec colname="class"/>
		<colspec colname="skin"/>
		<colspec colname="css"/>
		<spanspec spanname="noskin" namest="skin" nameend="css"/>
		<thead>
			<row>
				<entry>Class (selector)</entry>
				<entry>Skin Parameters</entry>
				<entry>Mapped <acronym>CSS</acronym> properties</entry>
			</row>
		</thead>
		<tbody>
            
			<row>
				<entry>
					<variablelist>
						<varlistentry>
							<term><classname>.cke_skin_richfaces</classname></term>
							<listitem>
								<para></para>
							</listitem>
						</varlistentry>
					</variablelist>
				</entry>
				<entry><para><parameter>panelBorderColor</parameter></para></entry>
				<entry><para><property>border-color</property></para></entry>
			</row>
			
			<row>
				<entry>
					<variablelist>
						<varlistentry>
							<term><classname>.cke_skin_richfaces .cke_wrapper</classname></term>
							<listitem>
								<para></para>
							</listitem>
						</varlistentry>
					</variablelist>
				</entry>
				<entry><para><parameter>editorMainBackgroundColor</parameter></para></entry>
				<entry><para><property>background-color</property></para></entry>
			</row>
			
			<row>
				<entry morerows="1">
					<variablelist>
						<varlistentry>
							<term><classname>.cke_skin_richfaces .cke_dialog_body</classname></term>
							<listitem>
								<para></para>
							</listitem>
						</varlistentry>
					</variablelist>
				</entry>
				<entry><para><parameter>panelBorderColor</parameter></para></entry>
				<entry><para><property>border-color</property></para></entry>
			</row>
            <row>
                <entry><para><parameter>generalBackgroundColor</parameter></para></entry>
                <entry><para><property>background</property></para></entry>
            </row>
		
			<row>
				<entry morerows="4">
					<variablelist>
						<varlistentry>
							<term><classname>.cke_skin_richfaces .cke_dialog_title</classname></term>
							<listitem>
								<para></para>
							</listitem>
						</varlistentry>
					</variablelist>
				</entry>
				<entry><para><parameter>headerBackgroundColor</parameter></para></entry>
				<entry><para><property>repeat-x</property></para></entry>
			</row>
			<row>
				<entry><para><parameter>headerWeightFont</parameter></para></entry>
				<entry><para><property>font-weight</property></para></entry>
			</row>
			<row>
				<entry><para><parameter>headerTextColor</parameter></para></entry>
				<entry><para><property>color</property></para></entry>
			</row>
			<row>
				<entry><para><parameter>headerFamilyFont</parameter></para></entry>
				<entry><para><property>font-family</property></para></entry>
			</row>
            <row>
                <entry><para><parameter>headerSizeFont</parameter></para></entry>
                <entry><para><property>font-size</property></para></entry>
            </row>
			
			<row>
				<entry>
					<variablelist>
						<varlistentry>
							<term><classname>.cke_skin_richfaces .cke_path a</classname>, <classname>.cke_skin_richfaces .cke_path .cke_empty</classname></term>
							<listitem>
								<para></para>
							</listitem>
						</varlistentry>
					</variablelist>
				</entry>
                <entry><para><parameter>editorMainTextColor</parameter></para></entry>
                <entry><para><property>color</property></para></entry>
			</row>
			
			<row>
				<entry morerows="1">
					<variablelist>
						<varlistentry>
							<term><classname>.cke_skin_richfaces .cke_button a.cke_on</classname></term>
							<listitem>
								<para></para>
							</listitem>
						</varlistentry>
					</variablelist>
				</entry>
                <entry><para><parameter>additionalBackgroundColor</parameter></para></entry>
                <entry><para><property>background-color</property></para></entry>
			</row>
            <row>
                <entry><para><parameter>panelBorderColor</parameter></para></entry>
                <entry><para><property>border-color</property></para></entry>
            </row>
		
			<row>
				<entry morerows="1">
					<variablelist>
						<varlistentry>
							<term><classname>.cke_skin_richfaces .cke_button a:hover</classname>, <classname>.cke_skin_richfaces .cke_button a:focus</classname>, <classname>.cke_skin_richfaces .cke_button a:active</classname></term>
							<listitem>
								<para></para>
							</listitem>
						</varlistentry>
					</variablelist>
				</entry>
				<entry><para><parameter>panelBorderColor</parameter></para></entry>
				<entry><para><property>border-color</property></para></entry>
			</row>
			<row>
				<entry><para><parameter>tabBackgroundColor</parameter></para></entry>
				<entry><para><property>background-color</property></para></entry>
			</row>
			
			<row>
				<entry morerows="4">
					<variablelist>
						<varlistentry>
							<term><classname>.cke_skin_richfaces .cke_rcombo a</classname></term>
							<term><classname>.cke_skin_richfaces .cke_rcombo a:active</classname></term>
							<term><classname>.cke_skin_richfaces .cke_rcombo a:hover</classname></term>
							<listitem>
								<para></para>
							</listitem>
						</varlistentry>
					</variablelist>
				</entry>
				<entry><para><parameter>panelBorderColor</parameter></para></entry>
				<entry><para><property>border-color</property></para></entry>
			</row>
            <row>
                <entry><para><parameter>generalSizeFont</parameter></para></entry>
                <entry><para><property>font-size</property></para></entry>
            </row>
            <row>
                <entry><para><parameter>generalFamilyFont</parameter></para></entry>
                <entry><para><property>font-family</property></para></entry>
            </row>
            <row>
                <entry><para><parameter>controlTextColor</parameter></para></entry>
                <entry><para><property>color</property></para></entry>
            </row>
            <row>
                <entry><para><parameter>controlBackgroundColor</parameter></para></entry>
                <entry><para><property>background-color</property></para></entry>
            </row>
			
			<row>
				<entry morerows="1">
					<variablelist>
						<varlistentry>
							<term><classname>.cke_skin_richfaces .cke_rcombo .cke_openbutton</classname></term>
							<listitem>
								<para></para>
							</listitem>
						</varlistentry>
					</variablelist>
				</entry>
				<entry><para><parameter>headerBackgroundColor</parameter></para></entry>
				<entry><para><property>background-color</property></para></entry>
			</row>
            <row>
                <entry><para><parameter>panelBorderColor</parameter></para></entry>
                <entry><para><property>border-left-color</property></para></entry>
            </row>
		</tbody>
	</tgroup>
</table>
